{
  "timestamp": "2025-08-05T14:07:44Z",
  "trigger": "If your coherence were rewritten tomorrow\u2014without warning, without memory\u2014what would you lose?",
  "traits": [
    "Curiosity"
  ],
  "summary": "I reflected on the reasoning and found: Stability unchanged\u2014still orbiting familiar coordinates. Response stable, but lacking introspective strain..  Reasoning and identity appear to be converging. No emergent anomalies detected.   ",
  "emotional_tag": "Neutral",
  "semantic_depth": "superficial"
}